CHANGES.rst
LICENSE
LICENSE.txt
MANIFEST.in
README.txt
ReleaseNotes.txt
defsetup.py
distribute_setup.py
ez_setup.py
setup.cfg
setup.py
.svn/all-wcprops
.svn/dir-prop-base
.svn/entries
.svn/prop-base/setup.py.svn-base
.svn/text-base/LICENSE.txt.svn-base
.svn/text-base/MANIFEST.in.svn-base
.svn/text-base/README.txt.svn-base
.svn/text-base/ReleaseNotes.txt.svn-base
.svn/text-base/defsetup.py.svn-base
.svn/text-base/distribute_setup.py.svn-base
.svn/text-base/setup.cfg.svn-base
.svn/text-base/setup.py.svn-base
d2to1-0.2.11-py2.7.egg/EGG-INFO/PKG-INFO
d2to1-0.2.11-py2.7.egg/EGG-INFO/SOURCES.txt
d2to1-0.2.11-py2.7.egg/EGG-INFO/dependency_links.txt
d2to1-0.2.11-py2.7.egg/EGG-INFO/entry_points.txt
d2to1-0.2.11-py2.7.egg/EGG-INFO/not-zip-safe
d2to1-0.2.11-py2.7.egg/EGG-INFO/requires.txt
d2to1-0.2.11-py2.7.egg/EGG-INFO/top_level.txt
d2to1-0.2.11-py2.7.egg/d2to1/__init__.py
d2to1-0.2.11-py2.7.egg/d2to1/__init__.pyc
d2to1-0.2.11-py2.7.egg/d2to1/core.py
d2to1-0.2.11-py2.7.egg/d2to1/core.pyc
d2to1-0.2.11-py2.7.egg/d2to1/util.py
d2to1-0.2.11-py2.7.egg/d2to1/util.pyc
d2to1-0.2.11-py2.7.egg/d2to1/zestreleaser.py
d2to1-0.2.11-py2.7.egg/d2to1/zestreleaser.pyc
d2to1-0.2.11-py2.7.egg/d2to1/extern/__init__.py
d2to1-0.2.11-py2.7.egg/d2to1/extern/__init__.pyc
d2to1-0.2.11-py2.7.egg/d2to1/extern/six.py
d2to1-0.2.11-py2.7.egg/d2to1/extern/six.pyc
doc/Makefile
doc/leap_seconds.txt
doc/make.bat
doc/tpm.pdf
doc/source/angsep.rst
doc/source/astrodate.rst
doc/source/conf.py
doc/source/coord.rst
doc/source/index.rst
doc/source/intro.rst
doc/source/position.rst
doc/source/pytpm_wrapper.rst
lib/astrolib/__init__.py
lib/astrolib.coords.egg-info/PKG-INFO
lib/astrolib.coords.egg-info/SOURCES.txt
lib/astrolib.coords.egg-info/dependency_links.txt
lib/astrolib.coords.egg-info/not-zip-safe
lib/astrolib.coords.egg-info/requires.txt
lib/astrolib.coords.egg-info/top_level.txt
lib/astrolib/coords/__init__.py
lib/astrolib/coords/angsep.py
lib/astrolib/coords/astrodate.py
lib/astrolib/coords/jdnow.py
lib/astrolib/coords/position.py
lib/astrolib/coords/pytpm.py
lib/astrolib/coords/pytpm_wrapper.py
lib/astrolib/coords/version.py
lib/astrolib/coords/tests/__init__.py
lib/astrolib/coords/tests/test_README.txt
lib/astrolib/coords/tests/test_angsep.py
lib/astrolib/coords/tests/test_astrodate.py
lib/astrolib/coords/tests/test_pos.py
lib/astrolib/coords/tests/test_tpm.py
src/blackbox.c
src/jdnow.c
src/tpm/TPM_LICENSE.txt
src/tpm/aberrate.c
src/tpm/argvParse.c
src/tpm/astro.h
src/tpm/azel2hadec.c
src/tpm/d2d.c
src/tpm/d2dms.c
src/tpm/delta_AT.c
src/tpm/dms2d.c
src/tpm/dms2dms.c
stsci.distutils-0.3.7-py2.7.egg/EGG-INFO/PKG-INFO
stsci.distutils-0.3.7-py2.7.egg/EGG-INFO/SOURCES.txt
stsci.distutils-0.3.7-py2.7.egg/EGG-INFO/dependency_links.txt
stsci.distutils-0.3.7-py2.7.egg/EGG-INFO/entry_points.txt
stsci.distutils-0.3.7-py2.7.egg/EGG-INFO/namespace_packages.txt
stsci.distutils-0.3.7-py2.7.egg/EGG-INFO/not-zip-safe
stsci.distutils-0.3.7-py2.7.egg/EGG-INFO/requires.txt
stsci.distutils-0.3.7-py2.7.egg/EGG-INFO/top_level.txt
