Metadata-Version: 1.0
Name: astrolib.coords
Version: 0.39.5
Summary: Astronomical coordinates & angular separations (OO)
Home-page: http://www.astrolib.org
Author: Vicki Laidler
Author-email: help@stsci.edu
License: UNKNOWN
Platform: UNKNOWN
Classifier: Intended Audience :: Science/Research
Classifier: License :: OSI Approved :: BSD License
Classifier: Operating System :: OS Independent
Classifier: Programming Language :: Python
Classifier: Topic :: Scientific/Engineering :: Astronomy
Classifier: Topic :: Software Development :: Libraries :: Python Modules
